ryomen/__init__.py
ryomen/main.py
tests/__init__.py
tests/playground.py
tests/test_ryomen.py
ryomen-0.0.9.dist-info/LICENSE
ryomen-0.0.9.dist-info/METADATA
ryomen-0.0.9.dist-info/WHEEL
ryomen-0.0.9.dist-info/top_level.txt
ryomen-0.0.9.dist-info/zip-safe
ryomen-0.0.9.dist-info/RECORD
