Metadata-Version: 2.1
Name: ryomen
Version: 0.0.9
Summary: Ryomen
Home-page: https://github.com/buswinka/ryomen
Author: Chris Buswinka
Author-email: buswinka@g.harvard.edu
Classifier: Programming Language :: Python :: 3
Requires-Python: >=3.10
License-File: LICENSE
